FourBitALU/VerilogImplementation/alutestbed.v
// CO221-Digital Design Project phase 1 
// March 2016
// Testbed and the impllementation of a simple ALU 
// This is for those who go beyond the minimal implementation
// and implement the extra part (4 bit muliplier) as well


// Group number : 09
// Names of members : 
// 						U.C.H KANEWALA	(E/13/175)
//						S.L.B. KARUNARATHNE	(E/13/181)
//						S.K.N. KAVINDI (E/13/183) 


//topt level stimulus odule
module testbed;

	reg [3:0] A,B;
	reg load1,load2,run;
	wire [3:0] C; 
	reg signed [3:0] C_twoscomplement;
	reg [1:0] op_select;
	
	//load1 loads A, load2 load B, run gives the output C
	//C is the 4-bit output that comes from the accumulator
	//A and B are the two 4-bit inputs coming from switches
	//load1 is the load signal for operand 1 register
	//load2 is the load signal for operand 2 register
	//run is the load signal for the accumulator register 
	//op_select selects the operator : 00 is xor, 01 is add, 10 is subtract, 11 is multuply 	
	//you don't have to model switches or the 7-segment displays in Verilog
	ALU mu_alu(C,A,B,load1,load2,op_select,run);
	
	//used for representing C as twos complement for the purpose of printing negative numbers
	always @ (C)
		begin	
		C_twoscomplement=C;
	end	
	
	initial
	begin

		//generate files needed to plot the waveform
		//you can plot the waveform generated after running the simulator by using gtkwave
		$dumpfile("wavedata.vcd");
	    $dumpvars(0,testbed);

	
		//A = 5 and B = 2
		A=4'd5; B=4'd2; 
		#5 load1=1'b1;
		#5 load1=1'b0;
		#5 load2=1'b1;
		#5 load2=1'b0;
		#5 op_select=2'b00; 
		#5 run=1'b1;
		#5 run=1'b0;
		$display("%b ^ %b = %b",A,B,C);
		#5 op_select=2'b01; 
		#5 run=1'b1;
		#5 run=1'b0;
		$display("%d + %d = %d",A,B,C);
		#5 op_select=2'b10; 
		#5 run=1'b1;
		#5 run=1'b0; 
		$display("%d - %d = %d",A,B,C_twoscomplement);
		#5 op_select=2'b11; 
		#5 run=1'b1;
		#5 run=1'b0;
		$display("%d * %d = %d\n",A,B,C);

		//A = 2 and B = 5
		#5 A=4'd2; B=4'd5; 
		#5 load1=1'b1;
		#5 load1=1'b0;
		#5 load2=1'b1;
		#5 load2=1'b0;
		#5 op_select=2'b00; 
		#5 run=1'b1;
		#5 run=1'b0;
		$display("%b ^ %b = %b",A,B,C);
		#5 op_select=2'b01; 
		#5 run=1'b1;
		#5 run=1'b0;
		$display("%d + %d = %d",A,B,C);
		#5 op_select=2'b10; 
		#5 run=1'b1;
		#5 run=1'b0;
		$display("%d - %d = %d",A,B,C_twoscomplement);
		#5 op_select=2'b11; 
		#5 run=1'b1;
		#5 run=1'b0;
		$display("%d * %d = %d\n",A,B,C);

		//you can similarly add other testcases.	
		
		
	end
	
endmodule


//your modules should go here

module register(P,Q,load);
	
	input[3:0] P;
	input load;
	output[3:0] Q;
	
	reg[3:0] store;
	assign Q=store;
	
	always @ (posedge load)
	begin
		store=P;
	end
	
endmodule


module ALU(C,A,B,load1,load2,op_select,run);

input [3:0] A;
input [3:0] B;
input [1:0] op_select;

output [3:0] C;

input load1,load2,run;

//define wires
wire [3:0] D;
wire [3:0] X;
wire [3:0] AS;
wire [3:0] M;
wire [3:0] A0;
wire [3:0] B0;
wire [1:0] select;
wire L,w;

//setup the select bus to suit the circuit
and (select[1],op_select[0],op_select[1]);
xor (select[0],op_select[0],op_select[1]);

//setup the input registers
register inp_reg1(A,A0,load1);
register inp_reg2(B,B0,load2);

//setup the control line L which acts as a carry to the adder-subtractor module
not (w,op_select[0]);
and (L,op_select[1],w);

multiplier mult(M,A0,B0);	//setup the multiplier
xor_this x(X,A0,B0);	//setup the xor modules
add_sub as(AS,A0,B0,L);	//setup the adder-subtractor

//declare the input buses to the four 4-to-1 multiplexers
wire [3:0] M0;
wire [3:0] M1;
wire [3:0] M2;
wire [3:0] M3;

//assign values to the multiplexer input buses 
assign M0[0]=X[0];
assign M1[0]=X[1];
assign M2[0]=X[2];
assign M3[0]=X[3];

assign M0[1]=AS[0];
assign M1[1]=AS[1];
assign M2[1]=AS[2];
assign M3[1]=AS[3];

assign M0[2]=M[0];
assign M1[2]=M[1];
assign M2[2]=M[2];
assign M3[2]=M[3];

//setup four 4-to-1 multiplexers
multiplexer_4_1 m0(D[0],M0,select);
multiplexer_4_1 m1(D[1],M1,select);
multiplexer_4_1 m2(D[2],M2,select);
multiplexer_4_1 m3(D[3],M3,select);

register out_reg(D,C,run);	//setup the output register

endmodule


//multiplier
module multiplier(M,A,B);

input [3:0] A;
input [3:0] B;
output [3:0] M;

wire G;	//ground wire
wire [8:0] w;	//internal wiring

assign G=0;	//pull down G to ground

//first AND array
and and0(M[0],A[0],B[0]);
and and1(w[0],A[1],B[0]);
and and2(w[1],A[2],B[0]);
and and3(w[2],A[3],B[0]);

//second AND array
and and4(w[3],A[0],B[1]);
and and5(w[4],A[1],B[1]);
and and6(w[5],A[2],B[1]);

wire [3:0] A0;
wire [3:0] B0;
wire [3:0] S0;
wire CO0;

assign A0[0]=w[0];
assign A0[1]=w[1];
assign A0[2]=w[2];

assign B0[0]=w[3];
assign B0[1]=w[4];
assign B0[2]=w[5];

adder adder0(CO0,S0,A0,B0,G);

assign M[1]=S0[0];

and and7(w[6],A[0],B[2]);
and and8(w[7],A[1],B[2]);

wire [3:0] A1;
wire [3:0] B1;
wire [3:0] S1;
wire CO1;

assign A1[0]=S0[1];
assign A1[1]=S0[2];

assign B1[0]=w[6];
assign B1[1]=w[7];

adder adder1(CO1,S1,A1,B1,G);

assign M[2]=S1[0];

and and9(w[8],A[0],B[3]);

wire [3:0] A2;
wire [3:0] B2;
wire [3:0] S2;
wire CO2;

assign A2[0]=w[8];
assign B2[0]=S1[1];

adder adder2(CO2,S2,A2,B2,G);

assign M[3]=S2[0];

endmodule 


//4-bit adder
module adder(CO,S,A,B,CI);

input [3:0] A;
input [3:0] B;
input CI;

output [3:0] S;
output CO;

wire [2:0] w;	//internal wiring

//setup the line of full adders
full_adder fa0(w[0],S[0],A[0],B[0],CI);
full_adder fa1(w[1],S[1],A[1],B[1],w[0]);
full_adder fa2(w[2],S[2],A[2],B[2],w[1]);
full_adder fa3(CO,S[3],A[3],B[3],w[2]);

endmodule


//setup the adder-subtractor module
module add_sub(AS,A,B,L);

input [3:0] A;
input [3:0] B;
input L;	//L acts as control input which makes this module an adder when L=1 and a subtractor when L=0 

output [3:0] AS;

wire CO;
wire [3:0] D;
wire G;

assign G=0;

xor (D[0],B[0],L);
xor (D[1],B[1],L);
xor (D[2],B[2],L);
xor (D[3],B[3],L);

adder a0(C0,AS,A,D,L);

endmodule 



//xor module
module xor_this(X,A,B);

input [3:0] A;
input [3:0] B;

output [3:0] X;

xor xor0(X[0],A[0],B[0]);
xor xor1(X[1],A[1],B[1]);
xor xor2(X[2],A[2],B[2]);
xor xor3(X[3],A[3],B[3]);

endmodule



//4-to-1 multiplexer module
module multiplexer_4_1(Z,P,Q);

input [3:0] P;
input [1:0] Q;
output Z;

wire [5:0] w;	//internal wiring

not not0(w[0],Q[0]);
not not1(w[1],Q[1]);

and and0(w[2],w[0],w[1],P[0]);
and and1(w[3],w[1],Q[0],P[1]);
and and2(w[4],w[0],Q[1],P[2]);
and and3(w[5],Q[0],Q[1],P[3]);

or (Z,w[2],w[3],w[4],w[5]);

endmodule


//half-adder module
module half_adder(C,S,A,B);

input A,B;
output C,S;

xor (S,A,B);
and (C,A,B);

endmodule



//full-adder module
module full_adder(CO,S,A,B,CI);

input A,B,CI;
output CO,S;

wire [2:0] w;	//internal wiring

//implement using 2 half-adders
half_adder ha0(w[0],w[1],A,B);
half_adder ha1(w[2],S,w[1],CI);
or (CO,w[0],w[2]);

endmodule

FourBitALU/VerilogImplementation/wavedata.vcd
$date
	Fri Apr 01 13:26:23 2016
$end
$version
	Icarus Verilog
$end
$timescale
	1s
$end
$scope module testbed $end
$var wire 4 ! C [3:0] $end
$var reg 4 " A [3:0] $end
$var reg 4 # B [3:0] $end
$var reg 4 $ C_twoscomplement [3:0] $end
$var reg 1 % load1 $end
$var reg 1 & load2 $end
$var reg 2 ' op_select [1:0] $end
$var reg 1 ( run $end
$scope module mu_alu $end
$var wire 4 ) A [3:0] $end
$var wire 4 * B [3:0] $end
$var wire 1 + L $end
$var wire 1 % load1 $end
$var wire 1 & load2 $end
$var wire 2 , op_select [1:0] $end
$var wire 1 ( run $end
$var wire 1 - w $end
$var wire 2 . select [1:0] $end
$var wire 4 / X [3:0] $end
$var wire 4 0 M3 [3:0] $end
$var wire 4 1 M2 [3:0] $end
$var wire 4 2 M1 [3:0] $end
$var wire 4 3 M0 [3:0] $end
$var wire 4 4 M [3:0] $end
$var wire 4 5 D [3:0] $end
$var wire 4 6 C [3:0] $end
$var wire 4 7 B0 [3:0] $end
$var wire 4 8 AS [3:0] $end
$var wire 4 9 A0 [3:0] $end
$scope module as $end
$var wire 1 : G $end
$var wire 1 + L $end
$var wire 4 ; D [3:0] $end
$var wire 1 < C0 $end
$var wire 4 = B [3:0] $end
$var wire 4 > AS [3:0] $end
$var wire 4 ? A [3:0] $end
$scope module a0 $end
$var wire 4 @ B [3:0] $end
$var wire 1 + CI $end
$var wire 3 A w [2:0] $end
$var wire 4 B S [3:0] $end
$var wire 1 < CO $end
$var wire 4 C A [3:0] $end
$scope module fa0 $end
$var wire 1 D A $end
$var wire 1 E B $end
$var wire 1 + CI $end
$var wire 1 F CO $end
$var wire 3 G w [2:0] $end
$var wire 1 H S $end
$scope module ha0 $end
$var wire 1 D A $end
$var wire 1 E B $end
$var wire 1 I C $end
$var wire 1 J S $end
$upscope $end
$scope module ha1 $end
$var wire 1 K A $end
$var wire 1 + B $end
$var wire 1 L C $end
$var wire 1 H S $end
$upscope $end
$upscope $end
$scope module fa1 $end
$var wire 1 M A $end
$var wire 1 N B $end
$var wire 1 O CI $end
$var wire 1 P CO $end
$var wire 3 Q w [2:0] $end
$var wire 1 R S $end
$scope module ha0 $end
$var wire 1 M A $end
$var wire 1 N B $end
$var wire 1 S C $end
$var wire 1 T S $end
$upscope $end
$scope module ha1 $end
$var wire 1 U A $end
$var wire 1 O B $end
$var wire 1 V C $end
$var wire 1 R S $end
$upscope $end
$upscope $end
$scope module fa2 $end
$var wire 1 W A $end
$var wire 1 X B $end
$var wire 1 Y CI $end
$var wire 1 Z CO $end
$var wire 3 [ w [2:0] $end
$var wire 1 \ S $end
$scope module ha0 $end
$var wire 1 W A $end
$var wire 1 X B $end
$var wire 1 ] C $end
$var wire 1 ^ S $end
$upscope $end
$scope module ha1 $end
$var wire 1 _ A $end
$var wire 1 Y B $end
$var wire 1 ` C $end
$var wire 1 \ S $end
$upscope $end
$upscope $end
$scope module fa3 $end
$var wire 1 a A $end
$var wire 1 b B $end
$var wire 1 c CI $end
$var wire 1 < CO $end
$var wire 3 d w [2:0] $end
$var wire 1 e S $end
$scope module ha0 $end
$var wire 1 a A $end
$var wire 1 b B $end
$var wire 1 f C $end
$var wire 1 g S $end
$upscope $end
$scope module ha1 $end
$var wire 1 h A $end
$var wire 1 c B $end
$var wire 1 i C $end
$var wire 1 e S $end
$upscope $end
$upscope $end
$upscope $end
$upscope $end
$scope module inp_reg1 $end
$var wire 4 j P [3:0] $end
$var wire 1 % load $end
$var wire 4 k Q [3:0] $end
$var reg 4 l store [3:0] $end
$upscope $end
$scope module inp_reg2 $end
$var wire 4 m P [3:0] $end
$var wire 1 & load $end
$var wire 4 n Q [3:0] $end
$var reg 4 o store [3:0] $end
$upscope $end
$scope module m0 $end
$var wire 4 p P [3:0] $end
$var wire 2 q Q [1:0] $end
$var wire 1 r Z $end
$var wire 6 s w [5:0] $end
$upscope $end
$scope module m1 $end
$var wire 4 t P [3:0] $end
$var wire 2 u Q [1:0] $end
$var wire 1 v Z $end
$var wire 6 w w [5:0] $end
$upscope $end
$scope module m2 $end
$var wire 4 x P [3:0] $end
$var wire 2 y Q [1:0] $end
$var wire 1 z Z $end
$var wire 6 { w [5:0] $end
$upscope $end
$scope module m3 $end
$var wire 4 | P [3:0] $end
$var wire 2 } Q [1:0] $end
$var wire 1 ~ Z $end
$var wire 6 !" w [5:0] $end
$upscope $end
$scope module mult $end
$var wire 4 "" A [3:0] $end
$var wire 4 #" B [3:0] $end
$var wire 1 $" G $end
$var wire 9 %" w [8:0] $end
$var wire 4 &" S2 [3:0] $end
$var wire 4 '" S1 [3:0] $end
$var wire 4 (" S0 [3:0] $end
$var wire 4 )" M [3:0] $end
$var wire 1 *" CO2 $end
$var wire 1 +" CO1 $end
$var wire 1 ," CO0 $end
$var wire 4 -" B2 [3:0] $end
$var wire 4 ." B1 [3:0] $end
$var wire 4 /" B0 [3:0] $end
$var wire 4 0" A2 [3:0] $end
$var wire 4 1" A1 [3:0] $end
$var wire 4 2" A0 [3:0] $end
$scope module adder0 $end
$var wire 4 3" A [3:0] $end
$var wire 4 4" B [3:0] $end
$var wire 1 $" CI $end
$var wire 3 5" w [2:0] $end
$var wire 4 6" S [3:0] $end
$var wire 1 ," CO $end
$scope module fa0 $end
$var wire 1 7" A $end
$var wire 1 8" B $end
$var wire 1 $" CI $end
$var wire 1 9" CO $end
$var wire 3 :" w [2:0] $end
$var wire 1 ;" S $end
$scope module ha0 $end
$var wire 1 7" A $end
$var wire 1 8" B $end
$var wire 1 <" C $end
$var wire 1 =" S $end
$upscope $end
$scope module ha1 $end
$var wire 1 >" A $end
$var wire 1 $" B $end
$var wire 1 ?" C $end
$var wire 1 ;" S $end
$upscope $end
$upscope $end
$scope module fa1 $end
$var wire 1 @" A $end
$var wire 1 A" B $end
$var wire 1 B" CI $end
$var wire 1 C" CO $end
$var wire 3 D" w [2:0] $end
$var wire 1 E" S $end
$scope module ha0 $end
$var wire 1 @" A $end
$var wire 1 A" B $end
$var wire 1 F" C $end
$var wire 1 G" S $end
$upscope $end
$scope module ha1 $end
$var wire 1 H" A $end
$var wire 1 B" B $end
$var wire 1 I" C $end
$var wire 1 E" S $end
$upscope $end
$upscope $end
$scope module fa2 $end
$var wire 1 J" A $end
$var wire 1 K" B $end
$var wire 1 L" CI $end
$var wire 1 M" CO $end
$var wire 3 N" w [2:0] $end
$var wire 1 O" S $end
$scope module ha0 $end
$var wire 1 J" A $end
$var wire 1 K" B $end
$var wire 1 P" C $end
$var wire 1 Q" S $end
$upscope $end
$scope module ha1 $end
$var wire 1 R" A $end
$var wire 1 L" B $end
$var wire 1 S" C $end
$var wire 1 O" S $end
$upscope $end
$upscope $end
$scope module fa3 $end
$var wire 1 T" A $end
$var wire 1 U" B $end
$var wire 1 V" CI $end
$var wire 1 ," CO $end
$var wire 3 W" w [2:0] $end
$var wire 1 X" S $end
$scope module ha0 $end
$var wire 1 T" A $end
$var wire 1 U" B $end
$var wire 1 Y" C $end
$var wire 1 Z" S $end
$upscope $end
$scope module ha1 $end
$var wire 1 [" A $end
$var wire 1 V" B $end
$var wire 1 \" C $end
$var wire 1 X" S $end
$upscope $end
$upscope $end
$upscope $end
$scope module adder1 $end
$var wire 4 ]" A [3:0] $end
$var wire 4 ^" B [3:0] $end
$var wire 1 $" CI $end
$var wire 3 _" w [2:0] $end
$var wire 4 `" S [3:0] $end
$var wire 1 +" CO $end
$scope module fa0 $end
$var wire 1 a" A $end
$var wire 1 b" B $end
$var wire 1 $" CI $end
$var wire 1 c" CO $end
$var wire 3 d" w [2:0] $end
$var wire 1 e" S $end
$scope module ha0 $end
$var wire 1 a" A $end
$var wire 1 b" B $end
$var wire 1 f" C $end
$var wire 1 g" S $end
$upscope $end
$scope module ha1 $end
$var wire 1 h" A $end
$var wire 1 $" B $end
$var wire 1 i" C $end
$var wire 1 e" S $end
$upscope $end
$upscope $end
$scope module fa1 $end
$var wire 1 j" A $end
$var wire 1 k" B $end
$var wire 1 l" CI $end
$var wire 1 m" CO $end
$var wire 3 n" w [2:0] $end
$var wire 1 o" S $end
$scope module ha0 $end
$var wire 1 j" A $end
$var wire 1 k" B $end
$var wire 1 p" C $end
$var wire 1 q" S $end
$upscope $end
$scope module ha1 $end
$var wire 1 r" A $end
$var wire 1 l" B $end
$var wire 1 s" C $end
$var wire 1 o" S $end
$upscope $end
$upscope $end
$scope module fa2 $end
$var wire 1 t" A $end
$var wire 1 u" B $end
$var wire 1 v" CI $end
$var wire 1 w" CO $end
$var wire 3 x" w [2:0] $end
$var wire 1 y" S $end
$scope module ha0 $end
$var wire 1 t" A $end
$var wire 1 u" B $end
$var wire 1 z" C $end
$var wire 1 {" S $end
$upscope $end
$scope module ha1 $end
$var wire 1 |" A $end
$var wire 1 v" B $end
$var wire 1 }" C $end
$var wire 1 y" S $end
$upscope $end
$upscope $end
$scope module fa3 $end
$var wire 1 ~" A $end
$var wire 1 !# B $end
$var wire 1 "# CI $end
$var wire 1 +" CO $end
$var wire 3 ## w [2:0] $end
$var wire 1 $# S $end
$scope module ha0 $end
$var wire 1 ~" A $end
$var wire 1 !# B $end
$var wire 1 %# C $end
$var wire 1 &# S $end
$upscope $end
$scope module ha1 $end
$var wire 1 '# A $end
$var wire 1 "# B $end
$var wire 1 (# C $end
$var wire 1 $# S $end
$upscope $end
$upscope $end
$upscope $end
$scope module adder2 $end
$var wire 4 )# A [3:0] $end
$var wire 4 *# B [3:0] $end
$var wire 1 $" CI $end
$var wire 3 +# w [2:0] $end
$var wire 4 ,# S [3:0] $end
$var wire 1 *" CO $end
$scope module fa0 $end
$var wire 1 -# A $end
$var wire 1 .# B $end
$var wire 1 $" CI $end
$var wire 1 /# CO $end
$var wire 3 0# w [2:0] $end
$var wire 1 1# S $end
$scope module ha0 $end
$var wire 1 -# A $end
$var wire 1 .# B $end
$var wire 1 2# C $end
$var wire 1 3# S $end
$upscope $end
$scope module ha1 $end
$var wire 1 4# A $end
$var wire 1 $" B $end
$var wire 1 5# C $end
$var wire 1 1# S $end
$upscope $end
$upscope $end
$scope module fa1 $end
$var wire 1 6# A $end
$var wire 1 7# B $end
$var wire 1 8# CI $end
$var wire 1 9# CO $end
$var wire 3 :# w [2:0] $end
$var wire 1 ;# S $end
$scope module ha0 $end
$var wire 1 6# A $end
$var wire 1 7# B $end
$var wire 1 <# C $end
$var wire 1 =# S $end
$upscope $end
$scope module ha1 $end
$var wire 1 ># A $end
$var wire 1 8# B $end
$var wire 1 ?# C $end
$var wire 1 ;# S $end
$upscope $end
$upscope $end
$scope module fa2 $end
$var wire 1 @# A $end
$var wire 1 A# B $end
$var wire 1 B# CI $end
$var wire 1 C# CO $end
$var wire 3 D# w [2:0] $end
$var wire 1 E# S $end
$scope module ha0 $end
$var wire 1 @# A $end
$var wire 1 A# B $end
$var wire 1 F# C $end
$var wire 1 G# S $end
$upscope $end
$scope module ha1 $end
$var wire 1 H# A $end
$var wire 1 B# B $end
$var wire 1 I# C $end
$var wire 1 E# S $end
$upscope $end
$upscope $end
$scope module fa3 $end
$var wire 1 J# A $end
$var wire 1 K# B $end
$var wire 1 L# CI $end
$var wire 1 *" CO $end
$var wire 3 M# w [2:0] $end
$var wire 1 N# S $end
$scope module ha0 $end
$var wire 1 J# A $end
$var wire 1 K# B $end
$var wire 1 O# C $end
$var wire 1 P# S $end
$upscope $end
$scope module ha1 $end
$var wire 1 Q# A $end
$var wire 1 L# B $end
$var wire 1 R# C $end
$var wire 1 N# S $end
$upscope $end
$upscope $end
$upscope $end
$upscope $end
$scope module out_reg $end
$var wire 4 S# P [3:0] $end
$var wire 4 T# Q [3:0] $end
$var wire 1 ( load $end
$var reg 4 U# store [3:0] $end
$upscope $end
$scope module x $end
$var wire 4 V# A [3:0] $end
$var wire 4 W# B [3:0] $end
$var wire 4 X# X [3:0] $end
$upscope $end
$upscope $end
$upscope $end
$enddefinitions $end
#0
$dumpvars
bx X#
bx W#
bx V#
bx U#
bx T#
bx S#
xR#
xQ#
xP#
xO#
xN#
bx M#
xL#
zK#
zJ#
xI#
xH#
xG#
xF#
xE#
bx D#
xC#
xB#
zA#
z@#
x?#
x>#
x=#
x<#
x;#
bx :#
x9#
x8#
z7#
z6#
05#
x4#
x3#
x2#
x1#
b0xx 0#
x/#
x.#
x-#
bx ,#
bx +#
bzx *#
bzx )#
x(#
x'#
x&#
x%#
x$#
bx ##
x"#
z!#
z~"
x}"
x|"
x{"
xz"
xy"
bx x"
xw"
xv"
zu"
zt"
xs"
xr"
xq"
xp"
xo"
bx n"
xm"
xl"
xk"
xj"
0i"
xh"
xg"
xf"
xe"
b0xx d"
xc"
xb"
xa"
bx `"
bx _"
bzxx ^"
bzxx ]"
x\"
x["
xZ"
xY"
xX"
bx W"
xV"
zU"
zT"
xS"
xR"
xQ"
xP"
xO"
bx N"
xM"
xL"
xK"
xJ"
xI"
xH"
xG"
xF"
xE"
bx D"
xC"
xB"
xA"
x@"
0?"
x>"
x="
x<"
x;"
b0xx :"
x9"
x8"
x7"
bx 6"
bx 5"
bzxxx 4"
bzxxx 3"
bzxxx 2"
bzxx 1"
bzx 0"
bzxxx /"
bzxx ."
bzx -"
x,"
x+"
x*"
bx )"
bx ("
bx '"
bx &"
bx %"
0$"
bx #"
bx ""
bx !"
x~
bx }
bzxxx |
bx {
xz
bx y
bzxxx x
bx w
xv
bx u
bzxxx t
bx s
xr
bx q
bzxxx p
bx o
bx n
b10 m
bx l
bx k
b101 j
xi
xh
xg
xf
xe
bx d
xc
xb
xa
x`
x_
x^
x]
x\
bx [
xZ
xY
xX
xW
xV
xU
xT
xS
xR
bx Q
xP
xO
xN
xM
xL
xK
xJ
xI
xH
bx G
xF
xE
xD
bx C
bx B
bx A
bx @
bx ?
bx >
bx =
x<
bx ;
0:
bx 9
bx 8
bx 7
bx 6
bx 5
bx 4
bzxxx 3
bzxxx 2
bzxxx 1
bzxxx 0
bx /
bx .
x-
bx ,
x+
b10 *
b101 )
x(
bx '
x&
x%
bx $
b10 #
b101 "
bx !
$end
#5
b0xx W"
0\"
0V"
0M"
0S"
0L"
0C"
0I"
0B"
b0 5"
09"
b0x0 :"
0<"
b0x0 N"
0P"
b0x0 D"
0F"
bx0 n"
0p"
07"
0J"
0A"
0k"
bz0x0 2"
bz0x0 3"
bzx0x /"
bzx0x 4"
bz0x ."
bz0x ^"
bx0xx0x0x0 %"
bx0 d
0f
bx0 Q
0S
0a
1W
0M
1D
b101 9
b101 ?
b101 C
b101 k
b101 l
b101 ""
b101 V#
1%
#10
0%
#15
bx1 &"
bx1 ,#
11#
bx0xxxx {
14#
13#
1.#
bz1 -"
bz1 *#
b0xx x"
0}"
0e"
bx10 '"
bx10 `"
1o"
0v"
0h"
1r"
0m"
0g"
1q"
0a"
1j"
b10 n"
0s"
b0xx :#
0?#
bz10 1"
bz10 ]"
0l"
08#
0E"
1;"
bx101 ("
bx101 6"
1O"
bx00 _"
0c"
bx0 +#
0/#
0H"
1>"
1R"
bx0xxxx s
b0 D"
0G"
b10 :"
1="
b10 N"
1Q"
b0 d"
0f"
b10 0#
02#
bx0xx !"
0@"
18"
1K"
0b"
0-#
bz000 2"
bz000 3"
bz101 /"
bz101 4"
bz00 ."
bz00 ^"
bz0 0"
bz0 )#
bz0x1 3
bz0x1 p
bz1x1 2
bz1x1 t
bz0x1 1
bz0x1 x
bz1x0 0
bz1x0 |
b1010 4
b1010 )"
b101000 %"
b111 /
b111 X#
b10 7
b10 =
b10 n
b10 o
b10 #"
b10 W#
1&
#20
0&
#25
bz100 0
bz100 |
0e
0c
0Z
bz011 1
bz011 x
1\
0`
0Y
0P
bz111 2
bz111 t
1R
0V
0<
1r
1v
1z
bz011 3
bz011 p
0O
b111 8
b111 >
b111 B
1H
b0 A
0F
0i
b111 5
b111 S#
0~
1K
1U
1_
0h
1J
0I
b10 Q
1T
1^
b10 [
0]
b0 d
0g
b111 s
b111 w
b111 {
b11 !"
0E
1N
0X
0b
b10 ;
b10 @
b10 G
0L
b0 .
b0 q
b0 u
b0 y
b0 }
1-
0+
b0 '
b0 ,
#30
b111 $
b111 !
b111 6
b111 T#
b111 U#
1(
#35
0(
#40
b1010 s
b1010 w
b1010 {
b10 !"
b1 .
b1 q
b1 u
b1 y
b1 }
0-
b1 '
b1 ,
#45
1(
#50
0(
#55
0z
0~
1<
b10 {
b10 !"
1i
bz001 1
bz001 x
1c
bz100 0
bz100 |
b11 5
b11 S#
1r
0\
1Z
0e
0K
0U
0_
1h
b1010 s
1O
0J
1I
b0 Q
0T
0^
b1 [
1]
b110 d
1g
b101 A
1F
1E
0N
1X
1b
bz011 3
bz011 p
b1101 ;
b1101 @
b11 8
b11 >
b11 B
1H
b1 G
0L
1+
1-
b10 '
b10 ,
#60
b11 $
b11 !
b11 6
b11 T#
b11 U#
1(
#65
0(
#70
0`
0Y
0P
0<
0O
bz111 2
bz111 t
bz011 1
bz011 x
0c
bz100 0
bz100 |
1~
0F
1R
0V
1\
b0 A
0Z
0e
0i
1K
1U
1_
0h
0r
b1010 5
b1010 S#
1v
1J
b10 G
0I
b10 Q
1T
1^
b10 [
0]
b0 d
0g
0E
1N
0X
0b
bz011 3
bz011 p
b1 s
b10001 w
b1 {
b10001 !"
b10 ;
b10 @
b111 8
b111 >
b111 B
1H
0+
b10 .
b10 q
b10 u
b10 y
b10 }
0-
b11 '
b11 ,
#75
b1010 $
b1010 !
b1010 6
b1010 T#
b1010 U#
1(
#80
0(
#85
b101 #
b101 *
b101 m
b10 "
b10 )
b10 j
#90
0~
b1 !"
bz000 0
bz000 |
1z
bx0 &"
bx0 ,#
01#
b10001 {
04#
b0 0#
03#
0.#
b100 5
b100 S#
0v
bz0 -"
bz0 *#
1e"
bx01 '"
bx01 `"
0o"
b1 w
1h"
0r"
b10 d"
1g"
b0 n"
0q"
1a"
0j"
b100 4
b100 )"
bz01 1"
bz01 ]"
0;"
1E"
bx010 ("
bx010 6"
0O"
0>"
1H"
0R"
b0 :"
0="
b10 D"
1G"
b0 N"
0Q"
1Y
08"
1A"
0K"
1\
0R
b10 A
1P
b100 8
b100 >
b100 B
0H
bz010 /"
bz010 4"
bz000 3
bz000 p
bz000 2
bz000 t
bz110 1
bz110 x
0_
0U
0K
b10000 %"
b0 /
b0 X#
b0 [
0^
0T
b1 Q
1S
b0 G
0J
0W
1M
0D
b10 9
b10 ?
b10 C
b10 k
b10 l
b10 ""
b10 V#
1%
#95
0%
#100
0z
1~
b1 {
b10001 !"
b1010 5
b1010 S#
1v
0e"
bx1 &"
bx1 ,#
11#
b10001 w
0h"
14#
bz100 0
bz100 |
b0 d"
0g"
b10 0#
13#
0e
0a"
1.#
0c
b1010 4
b1010 )"
bz00 1"
bz00 ]"
bz1 -"
bz1 *#
0Z
1;"
bx001 ("
bx001 6"
0E"
bx10 '"
bx10 `"
1o"
0Y
1>"
0H"
1r"
1\
0`
1R
b0 A
0P
b111 8
b111 >
b111 B
1H
b10 :"
1="
b0 D"
0G"
b10 n"
1q"
1_
1U
1K
17"
0A"
1k"
b10 [
1^
1T
b10 Q
0S
b10 G
1J
bz001 2"
bz001 3"
bz000 /"
bz000 4"
bz10 ."
bz10 ^"
bz011 3
bz011 p
bz111 2
bz111 t
bz011 1
bz011 x
1X
0N
1E
b10000001 %"
b111 /
b111 X#
b101 ;
b101 @
b101 7
b101 =
b101 n
b101 o
b101 #"
b101 W#
1&
#105
0&
#110
1r
1z
1v
b111 5
b111 S#
0~
b111 s
b111 w
b111 {
b11 !"
b0 .
b0 q
b0 u
b0 y
b0 }
1-
b0 '
b0 ,
#115
b111 $
b111 !
b111 6
b111 T#
b111 U#
1(
#120
0(
#125
b1010 s
b1010 w
b1010 {
b10 !"
b1 .
b1 q
b1 u
b1 y
b1 }
0-
b1 '
b1 ,
#130
1(
#135
0(
#140
0v
b10 w
bz101 2
bz101 t
1z
1~
0R
b1010 {
b1010 !"
1Y
bz011 1
bz011 x
bz110 0
bz110 |
b1101 5
b1101 S#
1r
1P
1\
1e
0K
0U
0_
1h
b1010 s
0O
0J
0T
b1 Q
1S
b0 [
0^
b10 d
1g
b10 A
0F
0E
1N
0X
1b
bz011 3
bz011 p
b1010 ;
b1010 @
b1101 8
b1101 >
b1101 B
1H
b0 G
0L
1+
1-
b10 '
b10 ,
#145
b1101 $
b1101 !
b1101 6
b1101 T#
b1101 U#
1(
#150
0(
#155
0c
0Z
bz111 2
bz111 t
0Y
bz011 1
bz011 x
bz100 0
bz100 |
1v
1R
b0 A
0P
1\
0`
0e
1K
1U
1_
0h
0r
0z
b1010 5
b1010 S#
1~
b10 G
1J
1T
b10 Q
0S
b10 [
1^
b0 d
0g
1E
0N
1X
0b
bz011 3
bz011 p
b1 s
b10001 w
b1 {
b10001 !"
b101 ;
b101 @
b111 8
b111 >
b111 B
1H
0+
b10 .
b10 q
b10 u
b10 y
b10 }
0-
b11 '
b11 ,
#160
b1010 $
b1010 !
b1010 6
b1010 T#
b1010 U#
1(
#165
0(
